um6p_CC_learn/__init__.py
um6p_CC_learn/naive_bayes.py
um6p_CC_learn/pipeline.py
um6p_CC_learn/base/__init__.py
um6p_CC_learn/base/base.py
um6p_CC_learn/decomposition/__init__.py
um6p_CC_learn/decomposition/pca.py
um6p_CC_learn/ensemble/__init__.py
um6p_CC_learn/ensemble/bagging.py
um6p_CC_learn/ensemble/boosting.py
um6p_CC_learn/ensemble/random_forest.py
um6p_CC_learn/ensemble/stacking.py
um6p_CC_learn/ensemble/voting.py
um6p_CC_learn/feature_selection/RFE.py
um6p_CC_learn/feature_selection/__init__.py
um6p_CC_learn/feature_selection/select_from_model.py
um6p_CC_learn/feature_selection/variance_threshold.py
um6p_CC_learn/linear_model/__init__.py
um6p_CC_learn/linear_model/logistic_regression.py
um6p_CC_learn/linear_model/regression.py
um6p_CC_learn/metrics/__init__.py
um6p_CC_learn/metrics/auc.py
um6p_CC_learn/metrics/classification.py
um6p_CC_learn/metrics/cosine_distances.py
um6p_CC_learn/metrics/cosine_similarity.py
um6p_CC_learn/metrics/euclidian_distances.py
um6p_CC_learn/metrics/regression.py
um6p_CC_learn/metrics/roc_auc_score.py
um6p_CC_learn/metrics/roc_curve.py
um6p_CC_learn/model_selection/GridSearch.py
um6p_CC_learn/model_selection/__init__.py
um6p_CC_learn/model_selection/__split.py
um6p_CC_learn/model_selection/__validation.py
um6p_CC_learn/neighbors/KNeighborsClassifier.py
um6p_CC_learn/neighbors/__init__.py
um6p_CC_learn/neural_network/__init__.py
um6p_CC_learn/neural_network/multilayer_perceptron.py
um6p_CC_learn/preprocessing/__init__.py
um6p_CC_learn/preprocessing/check_X_y.py
um6p_CC_learn/preprocessing/encoding/__init__.py
um6p_CC_learn/preprocessing/encoding/label_encoder.py
um6p_CC_learn/preprocessing/encoding/one_hot_encoder.py
um6p_CC_learn/preprocessing/encoding/ordinal_encoder.py
um6p_CC_learn/preprocessing/imputation/__init__.py
um6p_CC_learn/preprocessing/imputation/missing_indicator.py
um6p_CC_learn/preprocessing/imputation/simple_imputer.py
um6p_CC_learn/preprocessing/transformers/__init__.py
um6p_CC_learn-0.2.5.dist-info/METADATA
um6p_CC_learn-0.2.5.dist-info/WHEEL
um6p_CC_learn-0.2.5.dist-info/top_level.txt
um6p_CC_learn-0.2.5.dist-info/RECORD
