Metadata-Version: 2.1
Name: um6p_CC_learn
Version: 0.2.5
Summary: A home made sklearn
Author: Sami AGOURRAM , Ilyass Hakkou
Author-email: Sami.AGOURRAM@um6p.ma
Classifier: Programming Language :: Python :: 3
Classifier: License :: OSI Approved :: MIT License
Classifier: Operating System :: OS Independent
Requires-Python: >=3.8
Requires-Dist: numpy >=1.21.0
Requires-Dist: scipy >=1.7.0
Requires-Dist: scikit-learn >=0.24.0
